pyspade_native/__init__.py
pyspade_native/__main__.py
pyspade_native/cmake/pyspade_native-config-version.cmake
pyspade_native/cmake/pyspade_native-config.cmake
pyspade_native/include/spade_ffi.h
pyspade_native/include/spade_wrapper.h
pyspade_native/lib/spade_ffi.dll
pyspade_native/lib/spade_ffi.dll.lib
pyspade_native/lib/spade_wrapper.dll
pyspade_native/lib/spade_wrapper.lib
dtcc_pyspade_native-0.1.3.dist-info/METADATA
dtcc_pyspade_native-0.1.3.dist-info/WHEEL
dtcc_pyspade_native-0.1.3.dist-info/licenses/LICENSE
dtcc_pyspade_native-0.1.3.dist-info/RECORD
