Metadata-Version: 2.2
Name: dtcc-pyspade-native
Version: 0.1.3
Summary: Spade C++ triangulation library packaged for Python projects (C++ only, no Python bindings)
Keywords: triangulation,delaunay,mesh,geometry,cdt,constrained-delaunay,cpp,native,spade
Author-Email: Vasilis Naserentin <vasilis.naserentin@chalmers.se>
Maintainer-Email: DTCC Dev Team <dtcc@chalmers.se>
License: MIT OR Apache-2.0
Classifier: Development Status :: 4 - Beta
Classifier: Intended Audience :: Developers
Classifier: Intended Audience :: Science/Research
Classifier: License :: OSI Approved :: MIT License
Classifier: License :: OSI Approved :: Apache Software License
Classifier: Programming Language :: C++
Classifier: Programming Language :: Rust
Classifier: Programming Language :: Python :: 3
Classifier: Programming Language :: Python :: 3.8
Classifier: Programming Language :: Python :: 3.9
Classifier: Programming Language :: Python :: 3.10
Classifier: Programming Language :: Python :: 3.11
Classifier: Programming Language :: Python :: 3.12
Classifier: Topic :: Software Development :: Libraries
Classifier: Topic :: Scientific/Engineering
Classifier: Topic :: Scientific/Engineering :: GIS
Classifier: Operating System :: OS Independent
Project-URL: Homepage, https://github.com/dtcc-platform/dtcc-pyspade-native
Project-URL: Documentation, https://dtcc-platform.github.io/dtcc-pyspade-native/
Project-URL: Repository, https://github.com/dtcc-platform/dtcc-pyspade-native
Project-URL: Issues, https://github.com/dtcc-platform/dtcc-pyspade-native/issues
Project-URL: Changelog, https://github.com/dtcc-platform/dtcc-pyspade-native/blob/main/CHANGELOG.md
Requires-Python: >=3.8
Provides-Extra: dev
Requires-Dist: pytest>=7.0; extra == "dev"
Requires-Dist: build>=0.10; extra == "dev"
Requires-Dist: twine>=4.0; extra == "dev"
